secret_garden/__init__.py
secret_garden/errors.py
secret_garden/parsers.py
secret_garden/readers.py
secret_garden/utils.py
secret_garden-1.0.1.dist-info/LICENCE.md
secret_garden-1.0.1.dist-info/METADATA
secret_garden-1.0.1.dist-info/WHEEL
secret_garden-1.0.1.dist-info/RECORD
