Metadata-Version: 2.1
Name: secret-garden
Version: 1.0.1
Summary: A better way to manage your dotenv variables
Keywords: dotenv,environment,variables,environment variables,dotenv variables,typed dotenv,typed environment variables,typed dotenv variables,dotenv management,environment management,secret variables
Author: DanielMuringe
Author-email: danielmuringe@gmail.com
Requires-Python: >=3.10,<4.0
Classifier: Development Status :: 3 - Alpha
Classifier: Intended Audience :: Developers
Classifier: License :: OSI Approved :: MIT License
Classifier: Operating System :: OS Independent
Classifier: Programming Language :: Python :: 3
Classifier: Programming Language :: Python :: 3.10
Classifier: Programming Language :: Python :: 3.11
Classifier: Programming Language :: Python :: 3.12
Classifier: Programming Language :: Python :: Implementation :: CPython
Requires-Dist: python-dotenv (>=1.0.1,<2.0.0)
Requires-Dist: pyyaml (>=6.0.1,<7.0.0)
Requires-Dist: toml (>=0.10.2,<0.11.0)
